huscy/project_consents/__init__.py
huscy/project_consents/admin.py
huscy/project_consents/apps.py
huscy/project_consents/constants.py
huscy/project_consents/forms.py
huscy/project_consents/models.py
huscy/project_consents/permissions.py
huscy/project_consents/serializer.py
huscy/project_consents/services.py
huscy/project_consents/urls.py
huscy/project_consents/views.py
huscy/project_consents/viewsets.py
huscy/project_consents/migrations/0001_initial.py
huscy/project_consents/migrations/__init__.py
huscy/project_consents/templates/project_consents/project_consent.html
huscy/project_consents/templates/project_consents/sign_project_consent.html
huscy/project_consents/templates/project_consents/signed_project_consent.html
huscy/project_consents/templates/project_consents/text_fragments/checkbox.html
huscy/project_consents/templates/project_consents/text_fragments/markdown.html
huscy/project_consents/templates/project_consents/text_fragments/page-break.html
huscy_project_consents-1.2.1.dist-info/METADATA
huscy_project_consents-1.2.1.dist-info/WHEEL
huscy_project_consents-1.2.1.dist-info/licenses/LICENSE
huscy_project_consents-1.2.1.dist-info/RECORD
